gfagui/__init__.py
gfagui/data_logger.py
gfagui/gfa.py
gfagui/god.py
gfagui/gui.py
gfagui/helper_functions.py
gfagui/logic.py
gfagui/main.py
gfagui/run_unit_tests.py
gfagui/signal.py
gfagui/tests.py
gfagui/view.py
gfagui/config/__init__.py
gfagui/config/config.py
gfagui/unit_tests/__init__.py
gfagui/unit_tests/unit_tests.py
gfagui/widgets/__init__.py
gfagui/widgets/adc.py
gfagui/widgets/alarms.py
gfagui/widgets/base.py
gfagui/widgets/ccd.py
gfagui/widgets/dac.py
gfagui/widgets/diagnostics.py
gfagui/widgets/discharge.py
gfagui/widgets/logs.py
gfagui/widgets/monitor_sensors.py
gfagui/widgets/offsets.py
gfagui/widgets/pid.py
gfagui/widgets/pwm.py
gfagui/widgets/qcheckboxreadonly.py
gfagui/widgets/settings.py
gfagui/widgets/telemetry.py
gfagui/widgets/versions.py
gfagui/widgets/ui/__init__.py
gfagui/widgets/ui/adc_ui.py
gfagui/widgets/ui/alarms_ui.py
gfagui/widgets/ui/ccd_ui.py
gfagui/widgets/ui/dac_ui.py
gfagui/widgets/ui/diagnostics_ui.py
gfagui/widgets/ui/discharge_ui.py
gfagui/widgets/ui/mainwindow_ui.py
gfagui/widgets/ui/monitor_sensors_ui.py
gfagui/widgets/ui/offsets_ui.py
gfagui/widgets/ui/pid_ui.py
gfagui/widgets/ui/plot_tab.py
gfagui/widgets/ui/pwm_ui.py
gfagui/widgets/ui/settings_ui.py
gfagui/widgets/ui/show_logs_ui.py
gfagui/widgets/ui/telemetry_ui.py
gfagui/widgets/ui/telemetry_widget.py
gfagui/widgets/ui/versions_ui.py
gfagui-1.0.0.dist-info/METADATA
gfagui-1.0.0.dist-info/WHEEL
gfagui-1.0.0.dist-info/entry_points.txt
gfagui-1.0.0.dist-info/top_level.txt
gfagui-1.0.0.dist-info/RECORD
