Metadata-Version: 2.1
Name: gfagui
Version: 1.0.0
Summary: UNKNOWN
Home-page: https://gitlab.pic.es/DESI-GFA/gfa_gui
Author: David Roman
Author-email: droman@ifae.es
License: BSD-3
Platform: UNKNOWN
Classifier: Development Status :: 5 - Production/Stable
Classifier: Intended Audience :: Developers
Classifier: License :: OSI Approved :: BSD License
Classifier: Programming Language :: Python :: 3
Requires-Dist: appdirs
Requires-Dist: coloredlogs
Requires-Dist: confuse
Requires-Dist: gfaaccesslib
Requires-Dist: gfafunctionality
Requires-Dist: guiqwt
Requires-Dist: PyQt5
Requires-Dist: pyqt-tools
